client/__init__.py
client/client_side.py
client/client/__init__.py
client/client/add_contact.py
client/client/database.py
client/client/del_contact.py
client/client/main_window.py
client/client/main_window_conv.py
client/client/start_dialog.py
client/client/transport.py
client/common/__init__.py
client/common/decorators.py
client/common/descryptors.py
client/common/errors.py
client/common/metaclasses.py
client/common/utils.py
client/common/variables.py
client/logs/__init__.py
client/logs/client_log_config.py
client/logs/log_config.py
client/logs/server_log_config.py
client/unit_tests/__init__.py
client/unit_tests/test_client.py
client/unit_tests/test_server.py
client/unit_tests/test_utils.py
xartiou_csa_client-0.0.1.dist-info/METADATA
xartiou_csa_client-0.0.1.dist-info/WHEEL
xartiou_csa_client-0.0.1.dist-info/top_level.txt
xartiou_csa_client-0.0.1.dist-info/RECORD
